decisions/__init__.py
decisions/policy.py
detectors/__init__.py
detectors/behavior_detector.py
detectors/classifier.py
detectors/embedding_detector.py
detectors/regex_detector.py
fusion/__init__.py
fusion/enhanced_risk_fusion.py
fusion/risk_fusion.py
openevln-0.1.2.dist-info/licenses/LICENSE
safety_types/__init__.py
safety_types/model.py
openevln-0.1.2.dist-info/METADATA
openevln-0.1.2.dist-info/WHEEL
openevln-0.1.2.dist-info/top_level.txt
openevln-0.1.2.dist-info/RECORD
