Metadata-Version: 2.4
Name: openevln
Version: 0.1.2
Summary: OpenEVLN: An open-source platform for evaluating learning and reasoning in AI agents.
Author-email: Sachin Raja <rajasachin1993@gmail.com>
License-Expression: MIT
Project-URL: Homepage, https://github.com/sachin-raja/openevln
Project-URL: Repository, https://github.com/sachin-raja/openevln
Project-URL: Bug Tracker, https://github.com/sachin-raja/openevln/issues
Classifier: Programming Language :: Python :: 3
Classifier: Operating System :: OS Independent
Classifier: Development Status :: 3 - Alpha
Classifier: Intended Audience :: Developers
Requires-Python: >=3.7
License-File: LICENSE
Requires-Dist: pyyaml>=6.0
Requires-Dist: dataclasses-json>=0.5.7
Requires-Dist: rich>=13.0.0
Requires-Dist: sentence-transformers>=2.2.0
Requires-Dist: scikit-learn>=1.3.0
Requires-Dist: numpy>=1.24.0
Requires-Dist: torch>=2.0.0
Provides-Extra: dev
Requires-Dist: pytest>=7.0.0; extra == "dev"
Requires-Dist: pytest-cov>=4.0.0; extra == "dev"
Requires-Dist: black>=23.0.0; extra == "dev"
Requires-Dist: isort>=5.12.0; extra == "dev"
Requires-Dist: mypy>=1.0.0; extra == "dev"
Dynamic: license-file
